{
    "dataList": [
        {
            "prefabName": "RockObj",
            "objectID": 0,
            "nameType": 3,
            "adjectives": []
        },
        {
            "prefabName": "RockObj",
            "objectID": 1,
            "nameType": 3,
            "adjectives": []
        },
        {
            "prefabName": "RockObj",
            "objectID": 2,
            "nameType": 3,
            "adjectives": []
        },
        {
            "prefabName": "WaterObj",
            "objectID": 3,
            "nameType": 6,
            "adjectives": []
        },
        {
            "prefabName": "RockObj",
            "objectID": 4,
            "nameType": 3,
            "adjectives": []
        },
        {
            "prefabName": "WaterObj",
            "objectID": 5,
            "nameType": 6,
            "adjectives": []
        },
        {
            "prefabName": "TreeObj",
            "objectID": 6,
            "nameType": 5,
            "adjectives": []
        },
        {
            "prefabName": "RoseObj",
            "objectID": 7,
            "nameType": 1,
            "adjectives": []
        },
        {
            "prefabName": "TreeObj",
            "objectID": 8,
            "nameType": 5,
            "adjectives": []
        },
        {
            "prefabName": "TreeObj",
            "objectID": 9,
            "nameType": 5,
            "adjectives": []
        },
        {
            "prefabName": "TreeObj",
            "objectID": 10,
            "nameType": 5,
            "adjectives": []
        },
        {
            "prefabName": "BallObj",
            "objectID": 11,
            "nameType": 2,
            "adjectives": []
        },
        {
            "prefabName": "BonfireObj",
            "objectID": 12,
            "nameType": 4,
            "adjectives": []
        },
        {
            "prefabName": "RockObj",
            "objectID": 13,
            "nameType": 3,
            "adjectives": []
        },
        {
            "prefabName": "TreeObj",
            "objectID": 14,
            "nameType": 5,
            "adjectives": []
        },
        {
            "prefabName": "WaterObj",
            "objectID": 15,
            "nameType": 6,
            "adjectives": []
        }
    ]
}